fitPlotpy/__init__.py
fitPlotpy/cdf.py
fitPlotpy/data_plots.py
fitPlotpy/fitted.py
fitPlotpy/hazard.py
fitPlotpy/moments.py
fitPlotpy/multi_fitted.py
fitPlotpy/pdf.py
fitPlotpy/sf.py
fitplotpy-0.1.0.dist-info/METADATA
fitplotpy-0.1.0.dist-info/WHEEL
fitplotpy-0.1.0.dist-info/top_level.txt
fitplotpy-0.1.0.dist-info/RECORD
