Metadata-Version: 2.4
Name: fitPlotpy
Version: 0.1.0
Summary: Probability distribution plotting
Author: Muhammad Osama
Author-email: muhammadosama0846@gmail.com
License: MIT
Requires-Dist: numpy
Requires-Dist: scipy
Requires-Dist: pandas
Requires-Dist: matplotlib
Requires-Dist: seaborn
Dynamic: author
Dynamic: author-email
Dynamic: license
Dynamic: requires-dist
Dynamic: summary
